setup.py
daemonic/__init__.py
daemonic/daemon.py
daemonic/pidfile.py
daemonic.egg-info/PKG-INFO
daemonic.egg-info/SOURCES.txt
daemonic.egg-info/dependency_links.txt
daemonic.egg-info/top_level.txt