Metadata-Version: 1.1
Name: daemonic
Version: 0.6
Summary: Properly set up UNIX daemon processes
Home-page: http://github.com/ericsuh/daemonic
Author: Eric Suh
Author-email: contact@ericsuh.com
License: UNKNOWN
Download-URL: https://github.com/ericsuh/daemonic/zipball/master
Platform: UNKNOWN
Classifier: Programming Language :: Python
Classifier: Programming Language :: Python :: 2
Classifier: Programming Language :: Python :: 3
Classifier: Operating System :: POSIX
Classifier: Operating System :: Unix
Classifier: Development Status :: 4 - Beta
Classifier: Intended Audience :: Developers
Classifier: License :: OSI Approved :: MIT License
Provides: daemonic
